r2g/__init__.py
r2g/errors.py
r2g/path.json
r2g/quick_test.json
r2g/taxid_to_species.json
r2g/local/__init__.py
r2g/local/assemblers.py
r2g/online/NCBIWWW_selenium.py
r2g/online/__init__.py
r2g/online/blast.py
r2g/online/fetch.py
r2g/utils/__init__.py
r2g/utils/dryrun.py
r2g-1.0.5.data/scripts/r2g
r2g-1.0.5.dist-info/LICENSE
r2g-1.0.5.dist-info/METADATA
r2g-1.0.5.dist-info/WHEEL
r2g-1.0.5.dist-info/top_level.txt
r2g-1.0.5.dist-info/RECORD
