Metadata-Version: 2.1
Name: r2g
Version: 1.0.5
Summary: A homology-based, computationally lightweight pipeline for discovering genes in the absence of an assembly
Home-page: https://yangwu91.github.io/r2g/
Author: Yang Wu
Author-email: wuyang@drwu.ga
Maintainer: Yang Wu
Maintainer-email: wuyang@drwu.ga
License: MIT
Platform: UNKNOWN
Classifier: Development Status :: 5 - Production/Stable
Classifier: Environment :: Console
Classifier: Intended Audience :: Science/Research
Classifier: License :: OSI Approved :: MIT License
Classifier: Natural Language :: English
Classifier: Operating System :: OS Independent
Classifier: Programming Language :: Python :: 3.6
Classifier: Programming Language :: Python :: 3.7
Classifier: Programming Language :: Python :: 3.8
Classifier: Topic :: Scientific/Engineering :: Bio-Informatics
Requires-Python: >=3.6
Requires-Dist: requests (~=2.24.0)
Requires-Dist: selenium (~=3.141.0)
Provides-Extra: gui
Requires-Dist: r2g-gui ; extra == 'gui'
Requires-Dist: PyQt5 (~=5.12.3) ; extra == 'gui'
Provides-Extra: test
Requires-Dist: pytest ; extra == 'test'
Requires-Dist: pytest-cov ; extra == 'test'
Requires-Dist: codecov ; extra == 'test'
